sparta_teams_notifications/__init__.py
sparta_teams_notifications/notifications.py
sparta_teams_notifications-1.2.6.dist-info/LICENSE
sparta_teams_notifications-1.2.6.dist-info/METADATA
sparta_teams_notifications-1.2.6.dist-info/WHEEL
sparta_teams_notifications-1.2.6.dist-info/top_level.txt
sparta_teams_notifications-1.2.6.dist-info/RECORD
