Metadata-Version: 2.2
Name: sparta-teams-notifications
Version: 1.2.6
Summary: Função de callback para integração entre airflow e teams
Author: Henrique Gomes Nunes
Author-email: henrique.gomes@sparta.com.br
License: MIT
Classifier: Programming Language :: Python :: 3
Classifier: License :: OSI Approved :: MIT License
Classifier: Operating System :: OS Independent
Requires-Python: >=3.11
License-File: LICENSE
Requires-Dist: apache-airflow
Requires-Dist: requests
Dynamic: author
Dynamic: author-email
Dynamic: classifier
Dynamic: license
Dynamic: requires-dist
Dynamic: requires-python
Dynamic: summary
